reponses_validator/__init__.pyi
reponses_validator/__init__.cp312-win_amd64.pyd
reponses_validator-0.1.0.dist-info/WHEEL
reponses_validator-0.1.0.dist-info/METADATA
reponses_validator-0.1.0.dist-info/RECORD
